in_toto_attestation/__init__.py
in_toto_attestation/predicates/link/v0/link_pb2.py
in_toto_attestation/predicates/provenance/v1/provenance_pb2.py
in_toto_attestation/predicates/scai/v0/scai.py
in_toto_attestation/predicates/scai/v0/scai_pb2.py
in_toto_attestation/predicates/test_result/v0/test_result_pb2.py
in_toto_attestation/predicates/vsa/v0/vsa_pb2.py
in_toto_attestation/v1/resource_descriptor.py
in_toto_attestation/v1/resource_descriptor_pb2.py
in_toto_attestation/v1/statement.py
in_toto_attestation/v1/statement_pb2.py
in_toto_attestation-0.9.2.dist-info/METADATA
in_toto_attestation-0.9.2.dist-info/WHEEL
in_toto_attestation-0.9.2.dist-info/RECORD
